{
  "id": "mdn-css__en-US_docs_Web_CSS_CSS_view_transitions",
  "source_id": "mdn-css",
  "source_name": "MDN CSS Reference",
  "category": "css_styling",
  "url": "https://developer.mozilla.org/en-US/docs/Web/CSS/CSS_view_transitions",
  "title": "CSS view transitions",
  "content": "CSS view transitions\nThe\nCSS view transitions\nmodule defines the behavior of the\nView Transition API\n, which allows developers to create animated transitions between different states within a document and across documents. This module also defines the CSS properties and pseudo-elements for styling these transitions.\nReference\nProperties\nview-transition-class\nview-transition-name\nAt-rules and descriptors\n@view-transition\nnavigation\ndescriptor\nSelectors and pseudo-elements\n:active-view-transition\n:active-view-transition-type()\n::view-transition\n::view-transition-image-pair()\n::view-transition-group()\n::view-transition-new()\n::view-transition-old()\nInterfaces\nCSSViewTransitionRule\nViewTransition\nViewTransition.skipTransition()\nmethod\nViewTransition.updateCallbackDone\nViewTransition.ready\nViewTransition.finished\nDocument.startViewTransition()\nmethod\nGuides\nUsing the View Transition API\nExplains how to create view transitions and customize transition animations, including manipulating active view transitions.\nRelated concepts\npagereveal\nevent\npageswap\nevent\nDocument.visibilityState\nCSS animations\nmodule\nanimation\n@keyframes\nCSSKeyframesRule\nCSSStyleRule\nWeb animations API\nCSS transforms\nmodule\ntransform\n<transform-function>\nSpecifications\nSpecification\nCSS View Transitions Module Level 1\nCSS View Transitions Module Level 2\nSee also\nPseudo-elements\nFunctional pseudo-classes\nLearn: Pseudo-classes and pseudo-elements\nHelp improve MDN\nLearn how to contribute\nThis page was last modified on\nNov 7, 2025\nby\nMDN contributors\n.\nView this page on GitHub\n\u00e2\u0080\u00a2\nReport a problem with this content",
  "content_markdown": "# CSS view transitions\n\nThe **CSS view transitions** module defines the behavior of the [View Transition API](/en-US/docs/Web/API/View_Transition_API), which allows developers to create animated transitions between different states within a document and across documents. This module also defines the CSS properties and pseudo-elements for styling these transitions.\n\n## [Reference](#reference)\n\n### [Properties](#properties)\n\n- [`view-transition-class`](/en-US/docs/Web/CSS/Reference/Properties/view-transition-class)\n- [`view-transition-name`](/en-US/docs/Web/CSS/Reference/Properties/view-transition-name)\n\n### [At-rules and descriptors](#at-rules_and_descriptors)\n\n- [`@view-transition`](/en-US/docs/Web/CSS/Reference/At-rules/@view-transition)\n  - [`navigation`](/en-US/docs/Web/CSS/Reference/At-rules/@view-transition#navigation) descriptor\n\n### [Selectors and pseudo-elements](#selectors_and_pseudo-elements)\n\n- [`:active-view-transition`](/en-US/docs/Web/CSS/Reference/Selectors/:active-view-transition)\n- [`:active-view-transition-type()`](/en-US/docs/Web/CSS/Reference/Selectors/:active-view-transition-type)\n- [`::view-transition`](/en-US/docs/Web/CSS/Reference/Selectors/::view-transition)\n- [`::view-transition-image-pair()`](/en-US/docs/Web/CSS/Reference/Selectors/::view-transition-image-pair)\n- [`::view-transition-group()`](/en-US/docs/Web/CSS/Reference/Selectors/::view-transition-group)\n- [`::view-transition-new()`](/en-US/docs/Web/CSS/Reference/Selectors/::view-transition-new)\n- [`::view-transition-old()`](/en-US/docs/Web/CSS/Reference/Selectors/::view-transition-old)\n\n### [Interfaces](#interfaces)\n\n- [`CSSViewTransitionRule`](/en-US/docs/Web/API/CSSViewTransitionRule)\n- [`ViewTransition`](/en-US/docs/Web/API/ViewTransition)\n  - [`ViewTransition.skipTransition()`](/en-US/docs/Web/API/ViewTransition/skipTransition) method\n  - [`ViewTransition.updateCallbackDone`](/en-US/docs/Web/API/ViewTransition/updateCallbackDone)\n  - [`ViewTransition.ready`](/en-US/docs/Web/API/ViewTransition/ready)\n  - [`ViewTransition.finished`](/en-US/docs/Web/API/ViewTransition/finished)\n- [`Document.startViewTransition()`](/en-US/docs/Web/API/Document/startViewTransition) method\n\n## [Guides](#guides)\n\n[Using the View Transition API](/en-US/docs/Web/API/View_Transition_API/Using)\n:   Explains how to create view transitions and customize transition animations, including manipulating active view transitions.\n\n## [Related concepts](#related_concepts)\n\n- [`pagereveal`](/en-US/docs/Web/API/PageRevealEvent \"pagereveal\") event\n- [`pageswap`](/en-US/docs/Web/API/PageSwapEvent \"pageswap\") event\n- [`Document.visibilityState`](/en-US/docs/Web/API/Document/visibilityState)\n- [CSS animations](/en-US/docs/Web/CSS/Guides/Animations) module\n\n  - [`animation`](/en-US/docs/Web/CSS/Reference/Properties/animation)\n  - [`@keyframes`](/en-US/docs/Web/CSS/Reference/At-rules/@keyframes)\n  - [`CSSKeyframesRule`](/en-US/docs/Web/API/CSSKeyframesRule)\n  - [`CSSStyleRule`](/en-US/docs/Web/API/CSSStyleRule)\n  - [Web animations API](/en-US/docs/Web/API/Web_Animations_API)\n- [CSS transforms](/en-US/docs/Web/CSS/Guides/Transforms) module\n\n  - [`transform`](/en-US/docs/Web/CSS/Reference/Properties/transform)\n  - [`<transform-function>`](/en-US/docs/Web/CSS/Reference/Values/transform-function)\n\n## [Specifications](#specifications)\n\n| Specification |\n| --- |\n| [CSS View Transitions Module Level 1](https://drafts.csswg.org/css-view-transitions-1/) |\n| [CSS View Transitions Module Level 2](https://drafts.csswg.org/css-view-transitions-2/) |\n\n## [See also](#see_also)\n\n- [Pseudo-elements](/en-US/docs/Web/CSS/Reference/Selectors/Pseudo-elements)\n- [Functional pseudo-classes](/en-US/docs/Web/CSS/Reference/Selectors/Pseudo-classes#functional_pseudo-classes)\n- [Learn: Pseudo-classes and pseudo-elements](/en-US/docs/Learn_web_development/Core/Styling_basics/Pseudo_classes_and_elements)\n\n## Help improve MDN\n\nWas this page helpful to you?\n\nYes\n\nNo\n\n[Learn how to contribute](/en-US/docs/MDN/Community/Getting_started)\n\nThis page was last modified on Nov 7, 2025 by [MDN contributors](/en-US/docs/Web/CSS/Guides/View_transitions/contributors.txt).\n\n[View this page on GitHub](https://github.com/mdn/content/blob/main/files/en-us/web/css/guides/view_transitions/index.md?plain=1 \"Folder: en-us/web/css/guides/view_transitions (Opens in a new tab)\") \u00e2\u0080\u00a2 [Report a problem with this content](https://github.com/mdn/content/issues/new?template=page-report.yml&mdn-url=https%3A%2F%2Fdeveloper.mozilla.org%2Fen-US%2Fdocs%2FWeb%2FCSS%2FGuides%2FView_transitions&metadata=%3C%21--+Do+not+make+changes+below+this+line+--%3E%0A%3Cdetails%3E%0A%3Csummary%3EPage+report+details%3C%2Fsummary%3E%0A%0A*+Folder%3A+%60en-us%2Fweb%2Fcss%2Fguides%2Fview_transitions%60%0A*+MDN+URL%3A+https%3A%2F%2Fdeveloper.mozilla.org%2Fen-US%2Fdocs%2FWeb%2FCSS%2FGuides%2FView_transitions%0A*+GitHub+URL%3A+https%3A%2F%2Fgithub.com%2Fmdn%2Fcontent%2Fblob%2Fmain%2Ffiles%2Fen-us%2Fweb%2Fcss%2Fguides%2Fview_transitions%2Findex.md%0A*+Last+commit%3A+https%3A%2F%2Fgithub.com%2Fmdn%2Fcontent%2Fcommit%2F85fccefc8066bd49af4ddafc12c77f35265c7e2d%0A*+Document+last+modified%3A+2025-11-07T15%3A58%3A06.000Z%0A%0A%3C%2Fdetails%3E \"This will take you to GitHub to file a new issue.\")",
  "tags": [
    "mdn",
    "css",
    "reference",
    "layout"
  ],
  "extracted_at": "2026-02-03T12:45:33.021399+00:00",
  "content_length": 1602,
  "content_hash": "102b668994308e1a"
}