{
  "session_id": 123,
  "run": 1,
  "engine": "groq",
  "model": "groq/compound",
  "task": "CRITIC: Create code review system\n\nCreate critic.py based on LATS/TextGrad patterns:\n\n1. Create critic.py with:\n   - CriticAgent class with review(code, context) method\n   - score_quality(code) -> 0.0-1.0 quality score\n   - generate_feedback(code, issues) -> improvement suggestions\n\n2. Quality scoring checks:\n   - Has proper error handling?\n   - Follows existing patterns in codebase?\n   - No obvious bugs or issues?\n   - Proper imports and dependencies?\n\n3. Add to grind_spawner.py (optional integ",
  "success": true,
  "duration_seconds": 9.613885,
  "cost_usd": 0.0022364,
  "tokens_input": 586,
  "tokens_output": 2649,
  "files_created": [],
  "error": null,
  "verification": {
    "verdict": "APPROVE",
    "reason": "No verifier",
    "cost": 0
  },
  "timestamp": "2026-02-04T02:41:53.948804"
}